app_plugins/__init__.py
app_plugins/admin.py
app_plugins/forms.py
app_plugins/library.py
app_plugins/models.py
app_plugins/tests.py
app_plugins/locale/fr/LC_MESSAGES/django.po
app_plugins/management/__init__.py
app_plugins/management/commands/__init__.py
app_plugins/management/commands/sync_plugins.py
app_plugins/templates/app_plugins/app_plugin.html
app_plugins/templates/app_plugins/plugin_point.html
app_plugins/templatetags/__init__.py
app_plugins/templatetags/app_plugins.py
app_plugins/test_app/__init__.py
app_plugins/test_app/manage.py
app_plugins/test_app/settings.py
app_plugins/test_app/site/__init__.py
app_plugins/test_app/site/models.py
app_plugins/test_app/site/urls.py
app_plugins/test_app/site/views.py
app_plugins/test_app/someapp/__init__.py
djangoplicity_caching_app_plugins-0.1.6.dist-info/LICENSE.rst
djangoplicity_caching_app_plugins-0.1.6.dist-info/METADATA
djangoplicity_caching_app_plugins-0.1.6.dist-info/WHEEL
djangoplicity_caching_app_plugins-0.1.6.dist-info/top_level.txt
djangoplicity_caching_app_plugins-0.1.6.dist-info/RECORD
