Metadata-Version: 2.1
Name: djangoplicity-caching-app-plugins
Version: 0.1.6
Summary: UNKNOWN
Home-page: https://github.com/djangoplicity/djangoplicity-caching-app-plugins
Author: Bruce Kroeze
Author-email: bruce@ecomsmith.com
License: UNKNOWN
Download-URL: https://github.com/djangoplicity/djangoplicity-caching-app-plugins/archive/refs/tags/0.1.6.tar.gz
Platform: UNKNOWN
Classifier: Development Status :: 3 - Alpha
Classifier: Environment :: Web Environment
Classifier: Intended Audience :: Developers
Classifier: License :: OSI Approved :: MIT License
Classifier: Operating System :: OS Independent
Classifier: Programming Language :: Python
Classifier: Framework :: Django
License-File: LICENSE.rst
Requires-Dist: setuptools
